{"stem":"afar","instances":[{"docId":"1904-02-12","docUri":"1904-02-12.html","score":1,"contexts":[{"form":"afar","weight":"1","pos":2045,"context":"...support Japan, France will certainly not watch from <mark>afar<\/mark>. Then, Germany and Italy also need to..."}]},{"docId":"1904-02-26","docUri":"1904-02-26.html","score":1,"contexts":[{"form":"afar","weight":"1","pos":2973,"context":".... Germany also does not want to watch from <mark>afar<\/mark> but wants to help Russia, only watching for..."}]},{"docId":"1904-02-19","docUri":"1904-02-19.html","score":1,"contexts":[{"form":"afar","weight":"1","pos":3112,"context":"...Austria will not be able to just watch from <mark>afar<\/mark> what happens on the Balkans - being significantly interested..."}]}]}