{"stem":"awar","instances":[{"docId":"1904-03-25","docUri":"1904-03-25.html","score":4,"contexts":[{"form":"aware","weight":"1","pos":3989,"context":"...a mediocre German man today. Everyone is also <mark>aware<\/mark> that if Queen Victoria of England went on her..."},{"form":"aware","weight":"1","pos":4554,"context":" “We are both well <mark>aware<\/mark> what the prince is and the danger looming over..."},{"form":"aware","weight":"1","pos":4592,"context":" “I am <mark>aware<\/mark> of that, dear father, that the Holy..."},{"form":"aware","weight":"1","pos":4662,"context":"...than my felicity and my life. I am <mark>aware<\/mark> I will be shredded in darkness and bitterness,..."}]},{"docId":"1904-02-12","docUri":"1904-02-12.html","score":3,"contexts":[{"form":"aware","weight":"1","pos":4777,"context":"...dare to question you today. But I am <mark>aware<\/mark> that you told me all your secrets as your..."},{"form":"aware","weight":"1","pos":5060,"context":"...?” - the student asked. “You are constantly <mark>aware<\/mark> that God is our guard, up to today..."},{"form":"aware","weight":"1","pos":5176,"context":"...evil. He knows the Jewish ways and is <mark>aware<\/mark> how to pursue. Additionally, he was very..."}]},{"docId":"1904-02-19","docUri":"1904-02-19.html","score":3,"contexts":[{"form":"aware","weight":"1","pos":2975,"context":"...revolutionaries way too much. And because they are <mark>aware<\/mark> that Turkey has to give in because of the..."},{"form":"aware","weight":"1","pos":3091,"context":"...the Macedonian question off their mind. Bulgarians are <mark>aware<\/mark> of their dark end and want to stop scampering..."},{"form":"aware","weight":"1","pos":4495,"context":"...as long as you live and you will be <mark>aware<\/mark> of what Kempe can do. Kneel and bow before..."}]},{"docId":"1904-03-08","docUri":"1904-03-08.html","score":1,"contexts":[{"form":"aware","weight":"1","pos":1955,"context":"...Delegate Markham asked the home secretary whether he was <mark>aware<\/mark> that 4,000 Polish Jews who do not know English..."}]},{"docId":"1904-03-22","docUri":"1904-03-22.html","score":1,"contexts":[{"form":"aware","weight":"1","pos":1734,"context":"...threats and no flattery helps. She is well <mark>aware<\/mark> "}]},{"docId":"1904-03-04","docUri":"1904-03-04.html","score":1,"contexts":[{"form":"aware","weight":"1","pos":4918,"context":"...decided to break the enemy lines although he was <mark>aware<\/mark> of the numbers. At that point there were..."}]}]}