{"stem":"bombard","instances":[{"docId":"1904-03-08","docUri":"1904-03-08.html","score":1,"contexts":[{"form":"bombarded","weight":"1","pos":2305,"context":"...the night from Sunday to Monday, Japanese battleships <mark>bombarded<\/mark> the fortress. The Russian ships did not shoot...","fid":"p__5"}]},{"docId":"1904-03-04","docUri":"1904-03-04.html","score":1,"contexts":[{"form":"bombard","weight":"1","pos":2715,"context":" <mark>bombard<\/mark> the Japanese fleet, but they needed to retreat...","fid":"p__8"}]}]}