{"stem":"braveri","instances":[{"docId":"1904-03-18","docUri":"1904-03-18.html","score":1,"contexts":[{"form":"bravery","weight":"1","pos":2621,"context":"...army. The commander General Kuropatkin hasn’t proven his <mark>bravery<\/mark> even once. His whole glory stems from being...","fid":"p__21"}]},{"docId":"1904-03-04","docUri":"1904-03-04.html","score":1,"contexts":[{"form":"bravery","weight":"1","pos":4654,"context":"...who withheld the enemy with a rare, fiery <mark>bravery<\/mark>. The result was that after the Polish king...","fid":"p__22"}]}]}