{"stem":"comfort","instances":[{"docId":"1904-02-26","docUri":"1904-02-26.html","score":1,"contexts":[{"form":"comforters","weight":"1","pos":1124,"context":"...curtains, sheep wool and silk, duvets and <mark>comforters<\/mark>, furniture fabrics etc. The latest novelties are...","fid":"p__4"}]},{"docId":"1904-02-19","docUri":"1904-02-19.html","score":1,"contexts":[{"form":"comforters","weight":"1","pos":5314,"context":"...curtains, sheep wool and silk, duvets and <mark>comforters<\/mark>, furniture fabrics etc. The latest novelties are...","fid":"p__4"}]}]}