{"stem":"correct","instances":[{"docId":"1904-03-25","docUri":"1904-03-25.html","score":3,"contexts":[{"form":"correct","weight":"1","pos":272,"context":" But not all of that is <mark>correct<\/mark>. Those who read the descriptions of the factories...","fid":"p__7"},{"form":"correct","weight":"1","pos":3779,"context":" But is this opinion <mark>correct<\/mark>? The oldest sentiment is not always the correct...","fid":"p__8"},{"form":"correct","weight":"1","pos":3786,"context":"...correct? The oldest sentiment is not always the <mark>correct<\/mark> one. We want to make our readers familiar...","fid":"p__8"}]},{"docId":"1904-03-18","docUri":"1904-03-18.html","score":2,"contexts":[{"form":"correct","weight":"1","pos":2296,"context":"...about the Russians having vacated Port Arthur is not <mark>correct<\/mark>. The fortress suffered heavily under Japanese bombardments,...","fid":"p__5"},{"form":"correct","weight":"1","pos":3271,"context":"...stars including dawn and sunset as well as the <mark>correct<\/mark> position of celestial bodies which show solar and lunar...","fid":"p__10"}]},{"docId":"1904-02-26","docUri":"1904-02-26.html","score":2,"contexts":[{"form":"correctly","weight":"1","pos":604,"context":".... They are not taking a stance and act <mark>correctly<\/mark> according to their duty.","fid":"p__4"},{"form":"correctly","weight":"1","pos":1077,"context":"...anticipated. This shows that I portrayed the situation <mark>correctly<\/mark>. The critique, what I have criticised was...","fid":"p__4"}]},{"docId":"1904-02-12","docUri":"1904-02-12.html","score":1,"contexts":[{"form":"correct","weight":"1","pos":209,"context":"All of those responses are <mark>correct<\/mark>. We have religious educators in every school -...","fid":"p__4"}]},{"docId":"1904-03-29","docUri":"1904-03-29.html","score":1,"contexts":[{"form":"correct","weight":"1","pos":2812,"context":"...from these books to prove that the denunciations are <mark>correct<\/mark>. ","fid":"p__16"}]},{"docId":"1904-02-19","docUri":"1904-02-19.html","score":1,"contexts":[{"form":"correctly","weight":"1","pos":1602,"context":"...the case here. The Italian government conducts itself <mark>correctly<\/mark> against Austria-Hungary, but they are constantly...","fid":"p__41"}]},{"docId":"1904-02-05","docUri":"1904-02-05.html","score":1,"contexts":[{"form":"correctly","weight":"1","pos":3132,"context":"...like it. - a liar as the world says <mark>correctly<\/mark>, nobody believes it. Russia has to proof,...","fid":"p__7"}]}]}