{"stem":"delight","instances":[{"docId":"1904-02-05","docUri":"1904-02-05.html","score":2,"contexts":[{"form":"delighted","weight":"1","pos":497,"context":"...Yiddish format, unlike every other newspaper sincerely simply <mark>delighted<\/mark> me - I have touched upon this matter several...","fid":"p__7"},{"form":"delighted","weight":"1","pos":4884,"context":"...a small portion of the public, which have <mark>delighted<\/mark> themselves with his commentary of the Talmud-Thora...","fid":"p__4"}]}]}