{"stem":"done","instances":[{"docId":"1904-03-25","docUri":"1904-03-25.html","score":8,"contexts":[{"form":"done","weight":"1","pos":251,"context":"...easily there; many emigrate because others who have <mark>done<\/mark> so, write “nice letters”, send presents to their...","fid":"p__8"},{"form":"done","weight":"1","pos":2206,"context":"...did not agree for which we tell him “well <mark>done<\/mark>!” as he could have done whatever he wanted...","fid":"p__4"},{"form":"done","weight":"1","pos":2209,"context":"...tell him “well done!” as he could have <mark>done<\/mark> whatever he wanted without an assembly. The assembly...","fid":"p__4"},{"form":"done","weight":"1","pos":2477,"context":"...to move anyone this time. As nothing was <mark>done<\/mark> the whole sitting, he at least wanted to...","fid":"p__8"},{"form":"done","weight":"1","pos":4890,"context":"...a good deed, even if he has not <mark>done<\/mark> it yet, is a good with God as...","fid":"p__13"},{"form":"done","weight":"1","pos":4896,"context":"..., is a good with God as he had <mark>done<\/mark> it already. The same applies to you as...","fid":"p__13"},{"form":"done","weight":"1","pos":4908,"context":"...daughter. For you, it is already a <mark>done<\/mark> deal that you will sacrifice yourself for the Yiddish...","fid":"p__13"},{"form":"done","weight":"1","pos":4969,"context":"...- \"you can know that this terrible Kneppe has <mark>done<\/mark> to us once before is lost - he can...","fid":"p__13"}]},{"docId":"1904-02-19","docUri":"1904-02-19.html","score":4,"contexts":[{"form":"done","weight":"1","pos":1311,"context":"...takes up to an hour of time and is <mark>done<\/mark> until the day is over. Therefore, the...","fid":"p__11"},{"form":"done","weight":"1","pos":1331,"context":"...subjects which are on the agenda. This is <mark>done<\/mark> constantly. However, if the majority wants to...","fid":"p__11"},{"form":"done","weight":"1","pos":2853,"context":"...to join the battle which no emperor before has <mark>done<\/mark>. ","fid":"p__20"},{"form":"done","weight":"1","pos":4592,"context":"...that you are not the first one who has <mark>done<\/mark> so and has become enemies with their father and...","fid":"p__14"}]},{"docId":"1904-02-05","docUri":"1904-02-05.html","score":2,"contexts":[{"form":"done","weight":"1","pos":869,"context":"..., the mingling with the other customs - has <mark>done<\/mark> to the Jewish peoples, we only need to...","fid":"p__3"},{"form":"done","weight":"1","pos":2900,"context":"...to actually help them. All of that consulting <mark>done<\/mark> for the provinces is a joke in of itself...","fid":"p__9"}]},{"docId":"1904-03-18","docUri":"1904-03-18.html","score":1,"contexts":[{"form":"done","weight":"1","pos":2344,"context":"...harbour are also heavily damaged. Nothing can be <mark>done<\/mark> against the enemy. ","fid":"p__6"}]},{"docId":"1904-02-12","docUri":"1904-02-12.html","score":1,"contexts":[{"form":"done","weight":"1","pos":199,"context":"...esteemed and highly renowned and everything is to be <mark>done<\/mark> in order to educate the children religiously. ","fid":"p__2"}]},{"docId":"1904-03-01","docUri":"1904-03-01.html","score":1,"contexts":[{"form":"done","weight":"1","pos":695,"context":"...oversea territories in Africa, even though it was <mark>done<\/mark> under great strain and with hardly any benefits....","fid":"p__32"}]}]}