{"stem":"european","instances":[{"docId":"1904-02-05","docUri":"1904-02-05.html","score":3,"contexts":[{"form":"European","weight":"1","pos":3195,"context":"...giant and strong country of Russia with which every <mark>European<\/mark> country is in conflict now, and the big...","fid":"p__6"},{"form":"European","weight":"1","pos":3239,"context":"...Jewish community in Japan, which until now the <mark>European<\/mark> reader has not had a lot of knowledge about...","fid":"p__6"},{"form":"European","weight":"1","pos":3448,"context":"...speaking very progressive and can be counted as a <mark>European<\/mark> country. ","fid":"p__6"}]}]}