{"stem":"everybodi","instances":[{"docId":"1904-02-12","docUri":"1904-02-12.html","score":1,"contexts":[{"form":"everybody","weight":"1","pos":4642,"context":"...law, and stole one another’s money - and <mark>everybody<\/mark> put the blame on the Jewish people to consume...","fid":"p__7"}]},{"docId":"1904-02-05","docUri":"1904-02-05.html","score":1,"contexts":[{"form":"everybody","weight":"1","pos":4943,"context":"...and his history, and therefore we think that <mark>everybody<\/mark> would be interested to read a short biography about...","fid":"p__8"}]},{"docId":"1904-03-08","docUri":"1904-03-08.html","score":1,"contexts":[{"form":"everybody","weight":"1","pos":1191,"context":"...take three days for another paper to arrive - <mark>everybody<\/mark> knows the news already. But if you publish...","fid":"p__9"}]},{"docId":"1904-03-25","docUri":"1904-03-25.html","score":1,"contexts":[{"form":"everybody","weight":"1","pos":4878,"context":"...do so. Our scholars learned from that, that <mark>everybody<\/mark> who plans to do a good deed, even...","fid":"p__14"}]}]}