{"stem":"father","instances":[{"docId":"1904-02-05","docUri":"1904-02-05.html","score":11,"contexts":[{"form":"fathers","weight":"1","pos":2160,"context":" We often see that the <mark>fathers<\/mark> now let their children go to school which stops...","fid":"p__6"},{"form":"father","weight":"1","pos":2184,"context":"...which educates them well and pious - the same <mark>father<\/mark> does not care about his daughters and as a...","fid":"p__6"},{"form":"father","weight":"1","pos":2422,"context":"...“German, son of a German” … If the <mark>father<\/mark> is strong enough to force the daughter to take...","fid":"p__6"},{"form":"father","weight":"1","pos":2458,"context":"...which means she doesn’t have to listen to her <mark>father<\/mark>, she threatens to throw herself into the water...","fid":"p__6"},{"form":"father","weight":"1","pos":2480,"context":"...- to go into a monastery … until the <mark>father<\/mark> has to give in. But if the father stands...","fid":"p__6"},{"form":"father","weight":"1","pos":2485,"context":"...the father has to give in. But if the <mark>father<\/mark> stands by his opinion and doesn’t want to succumb...","fid":"p__6"},{"form":"father","weight":"1","pos":2502,"context":"...is broken, there is a grudge held between <mark>father<\/mark> and daughter, they live angrily and bitter....","fid":"p__6"},{"form":"father","weight":"1","pos":2511,"context":"..., they live angrily and bitter. If the <mark>father<\/mark> wins, he forces his daughter","fid":"p__6"},{"form":"father","weight":"1","pos":2533,"context":"...like, if the daughter wins, forces the <mark>father<\/mark> to succumb, then the parent’s life is embittered...","fid":"p__7"},{"form":"father","weight":"1","pos":4808,"context":"...princess Stéphanie has handed over a complaint to her <mark>father<\/mark>, King of Belgium to hand over part of...","fid":"p__11"},{"form":"father","weight":"1","pos":4977,"context":"...Rashi comes from a family of scholars. His <mark>father<\/mark> was a great Talmud scholar, his mother was...","fid":"p__32"}]},{"docId":"1904-03-25","docUri":"1904-03-25.html","score":10,"contexts":[{"form":"father","weight":"1","pos":625,"context":"...As soon as the child can talk, the <mark>father<\/mark> is obligated to teach him the Torah: \"The...","fid":"p__10"},{"form":"father","weight":"1","pos":1531,"context":"...declare and announce all over the world for every <mark>father<\/mark> and mother to be wary of the debauched schools...","fid":"p__13"},{"form":"father","weight":"1","pos":1604,"context":" Every <mark>father<\/mark> is obliged to raise his children with tutors and..."},{"form":"father","weight":"1","pos":1746,"context":"...Torah reading, is it the duty of every <mark>father<\/mark> to visit the classroom often, to take care..."},{"form":"father","weight":"1","pos":1766,"context":"...ask each other to question the child. Every <mark>father<\/mark> and mother needs to know that their classroom is..."},{"form":"father","weight":"1","pos":4458,"context":" “Ah! Dear <mark>father<\/mark>, my grievances with what the prince threatened you...","fid":"p__6"},{"form":"father","weight":"1","pos":4544,"context":" “I am aware of that, dear <mark>father<\/mark>, that the Holy Creator leads the world and...","fid":"p__5"},{"form":"father","weight":"1","pos":4703,"context":"...I have indeed calculated all of that, dear <mark>father<\/mark>, I know very well that my whole life...","fid":"p__7"},{"form":"father","weight":"1","pos":4739,"context":"...life and my honour. You alone, dear <mark>father<\/mark>, taught me that every human has the duty...","fid":"p__7"},{"form":"father","weight":"1","pos":4902,"context":" “But my dear <mark>father<\/mark>, what shall we do?” - trust me -...","fid":"p__14"}]},{"docId":"1904-03-18","docUri":"1904-03-18.html","score":7,"contexts":[{"form":"father","weight":"1","pos":2708,"context":"...are concerned because as we all know, his <mark>father<\/mark>, Emperor Frederick, died because of cancer....","fid":"p__4"},{"form":"father","weight":"1","pos":4024,"context":"...did not immediately say yes, but as her <mark>father<\/mark> the rabbi did not give his blessing Sarah denied...","fid":"p__20"},{"form":"father","weight":"1","pos":4051,"context":"...all Jews, mainly the rabbi. Sarah’s <mark>father<\/mark> loved her dearly, because she was always very...","fid":"p__20"},{"form":"father","weight":"1","pos":4330,"context":"...that I have a hold over you, your <mark>father<\/mark>, and your people. Now is still time...","fid":"p__10"},{"form":"father","weight":"1","pos":4342,"context":"...to save yourself. I am sure that your <mark>father<\/mark> is not able to raise all of the money...","fid":"p__10"},{"form":"father","weight":"1","pos":4357,"context":"...demanded of him. But you can save your <mark>father<\/mark>. Agree to be my wife and I will...","fid":"p__10"},{"form":"father","weight":"1","pos":4435,"context":"...if you don’t go with me willingly, your <mark>father<\/mark> will be severely punished and I will conquer you...","fid":"p__16"}]},{"docId":"1904-03-29","docUri":"1904-03-29.html","score":5,"contexts":[{"form":"father","weight":"1","pos":2326,"context":"...the European calendar. He did not know his <mark>father<\/mark> as he died when his mother was still carrying...","fid":"p__9"},{"form":"father’s","weight":"1","pos":3780,"context":"...son Judah Leon Abravanel married the daughter of his <mark>father’s<\/mark> associate, Don Abraham Senior. His younger son...","fid":"p__22"},{"form":"father","weight":"1","pos":4153,"context":"...called to him, Don David Senior. The <mark>father<\/mark> entered a cabinet with him and explained his bitter...","fid":"p__17"},{"form":"father","weight":"1","pos":4176,"context":"...ocean of tears for God in heaven. The <mark>father<\/mark> swore a holy oath with the son that he...","fid":"p__17"},{"form":"father’s","weight":"1","pos":4323,"context":"...formerly called Don David Senior, was offered his <mark>father’s<\/mark> position by the king. But he declined and...","fid":"p__17"}]},{"docId":"1904-02-19","docUri":"1904-02-19.html","score":1,"contexts":[{"form":"father","weight":"1","pos":4589,"context":"...has done so and has become enemies with their <mark>father<\/mark> and mother, their brothers and the end of...","fid":"p__12"}]}]}