{"stem":"fine","instances":[{"docId":"1904-02-19","docUri":"1904-02-19.html","score":6,"contexts":[{"form":"Fine","weight":"1","pos":4924,"context":" <mark>Fine<\/mark> tea  ","fid":"div__13"},{"form":"fine","weight":"1","pos":4936,"context":"..., write to the address below, 1 kg <mark>fine<\/mark>, pure tea only 6 crowns. There is...","fid":"p__11"},{"form":"fine","weight":"1","pos":5150,"context":"...Hungary. Everything duty-free 5 kg Santos <mark>fine<\/mark> 6 guildes - 5 kg Santos prima 6.20 guildes...","fid":"p__5"},{"form":"fine","weight":"1","pos":5157,"context":"...kg Santos prima 6.20 guildes. - 5kg Kuba <mark>fine<\/mark> 7.50 guildes - 5kg Kuba prima 7.90 guildes -...","fid":"p__5"},{"form":"fine","weight":"1","pos":5176,"context":"...-Java 7.60 guildes - 5 kg Ceylon super <mark>fine<\/mark> 9 guildes - 5 kg San Salvador 7 guildes...","fid":"p__5"},{"form":"fine","weight":"1","pos":5189,"context":"...very strong 7.50 guildes - 5 kg Mokka super <mark>fine<\/mark> 9.20 guildes","fid":"p__5"}]},{"docId":"1904-02-05","docUri":"1904-02-05.html","score":4,"contexts":[{"form":"fine","weight":"1","pos":5654,"context":" 5 kg Santos <mark>fine<\/mark> 6 guildes - 5 kg Santos prima 6.20 guildes...","fid":"p__14"},{"form":"fine","weight":"1","pos":5661,"context":"...kg Santos prima 6.20 guildes. - 5kg Cuba <mark>fine<\/mark> 7.50 guildes - 5kg prima 7.90 guildes - 5...","fid":"p__14"},{"form":"fine","weight":"1","pos":5677,"context":"...-Java 7.60 guildes - 5 kg Ceylon super <mark>fine<\/mark> 9 guildes - 5 kg San Salvador 7 guildes...","fid":"p__14"},{"form":"fine","weight":"1","pos":5690,"context":"...very strong 7.50 guildes - 5 kg Mokka super <mark>fine<\/mark> 9.20 guildes ","fid":"p__14"}]},{"docId":"1904-02-12","docUri":"1904-02-12.html","score":2,"contexts":[{"form":"Fine","weight":"1","pos":5311,"context":" <mark>Fine<\/mark> tea  ","fid":"div__13"},{"form":"fine","weight":"1","pos":5323,"context":"..., write to the address below, 1 kg <mark>fine<\/mark>, pure tea only 6 crowns. There is...","fid":"p__11"}]}]}