{"stem":"geniun","instances":[{"docId":"1904-02-05","docUri":"1904-02-05.html","score":8,"contexts":[{"form":"Geniune","weight":"1","pos":4,"context":" The <mark>Geniune<\/mark> Jew    "},{"form":"Geniune","weight":"1","pos":16,"context":"   The <mark>Geniune<\/mark> Jew costs                     "},{"form":"Geniune","weight":"1","pos":72,"context":" The <mark>Geniune<\/mark> Jew       [1]         "},{"form":"Geniune","weight":"1","pos":82,"context":"\"The <mark>Geniune<\/mark> Jew\"","fid":"p__3"},{"form":"Geniune","weight":"1","pos":278,"context":"\"The <mark>Geniune<\/mark> Jew\"."},{"form":"Geniune","weight":"1","pos":423,"context":"    \"The <mark>Geniune<\/mark> Jew\" costs             "},{"form":"Geniune","weight":"1","pos":584,"context":"...written by another class of writers, and “The <mark>Geniune<\/mark> Jew” on the other hand will be in another...","fid":"p__7"},{"form":"“Geniune","weight":"1","pos":843,"context":"..., who hopefully will understand the value of the <mark>“Geniune<\/mark> Jew”. ","fid":"p__9"}]},{"docId":"1904-02-12","docUri":"1904-02-12.html","score":2,"contexts":[{"form":"Geniune","weight":"1","pos":4,"context":" The <mark>Geniune<\/mark> Jew    "},{"form":"Geniune","weight":"1","pos":16,"context":"   The <mark>Geniune<\/mark> Jew costs                     "}]},{"docId":"1904-03-29","docUri":"1904-03-29.html","score":2,"contexts":[{"form":"Geniune","weight":"1","pos":4,"context":" The <mark>Geniune<\/mark> Jew    "},{"form":"Geniune","weight":"1","pos":16,"context":"   The <mark>Geniune<\/mark> Jew costs                     "}]},{"docId":"1904-03-01","docUri":"1904-03-01.html","score":2,"contexts":[{"form":"Geniune","weight":"1","pos":4,"context":" The <mark>Geniune<\/mark> jew    "},{"form":"Geniune","weight":"1","pos":16,"context":"   The <mark>Geniune<\/mark> Jew costs                     "}]},{"docId":"1904-03-11","docUri":"1904-03-11.html","score":2,"contexts":[{"form":"Geniune","weight":"1","pos":4,"context":" The <mark>Geniune<\/mark> Jew    "},{"form":"Geniune","weight":"1","pos":16,"context":"   The <mark>Geniune<\/mark> Jew costs                     "}]},{"docId":"1904-03-15","docUri":"1904-03-15.html","score":2,"contexts":[{"form":"Geniune","weight":"1","pos":4,"context":" The <mark>Geniune<\/mark> Jew    "},{"form":"Geniune","weight":"1","pos":16,"context":"   The <mark>Geniune<\/mark> Jew costs                     "}]},{"docId":"1904-03-22","docUri":"1904-03-22.html","score":2,"contexts":[{"form":"Geniune","weight":"1","pos":4,"context":" The <mark>Geniune<\/mark> Jew    "},{"form":"Geniune","weight":"1","pos":16,"context":"   The <mark>Geniune<\/mark> Jew costs                     "}]},{"docId":"1904-03-08","docUri":"1904-03-08.html","score":2,"contexts":[{"form":"Geniune","weight":"1","pos":4,"context":" The <mark>Geniune<\/mark> jew    "},{"form":"Geniune","weight":"1","pos":16,"context":"   The <mark>Geniune<\/mark> Jew costs                     "}]},{"docId":"1904-03-25","docUri":"1904-03-25.html","score":2,"contexts":[{"form":"Geniune","weight":"1","pos":4,"context":" The <mark>Geniune<\/mark> Jew    "},{"form":"Geniune","weight":"1","pos":16,"context":"   The <mark>Geniune<\/mark> Jew costs                     "}]},{"docId":"1904-02-26","docUri":"1904-02-26.html","score":2,"contexts":[{"form":"Geniune","weight":"1","pos":4,"context":" The <mark>Geniune<\/mark> Jew    "},{"form":"Geniune","weight":"1","pos":16,"context":"   The <mark>Geniune<\/mark> Jew costs                     "}]},{"docId":"1904-02-19","docUri":"1904-02-19.html","score":2,"contexts":[{"form":"Geniune","weight":"1","pos":4,"context":" The <mark>Geniune<\/mark> jew    "},{"form":"Geniune","weight":"1","pos":16,"context":"   The <mark>Geniune<\/mark> Jew costs                     "}]},{"docId":"1904-03-04","docUri":"1904-03-04.html","score":2,"contexts":[{"form":"Geniune","weight":"1","pos":4,"context":" The <mark>Geniune<\/mark> jew    "},{"form":"Geniune","weight":"1","pos":16,"context":"   The <mark>Geniune<\/mark> Jew costs                     "}]},{"docId":"1904-03-18","docUri":"1904-03-18.html","score":2,"contexts":[{"form":"Geniune","weight":"1","pos":4,"context":" The <mark>Geniune<\/mark> Jew    "},{"form":"Geniune","weight":"1","pos":16,"context":"   The <mark>Geniune<\/mark> Jew costs                     "}]}]}