{"stem":"geniun","instances":[{"docId":"1904-02-05","docUri":"1904-02-05.html","score":3,"contexts":[{"form":"Geniune","weight":"1","pos":4,"context":"The <mark>Geniune<\/mark> Jew"},{"form":"Geniune","weight":"1","pos":16,"context":"The <mark>Geniune<\/mark> Jew costs"},{"form":"Geniune","weight":"1","pos":141,"context":"\"The <mark>Geniune<\/mark> Jew\" costs"}]},{"docId":"1904-03-08","docUri":"1904-03-08.html","score":2,"contexts":[{"form":"Geniune","weight":"1","pos":4,"context":"The <mark>Geniune<\/mark> Jew"},{"form":"Geniune","weight":"1","pos":16,"context":"The <mark>Geniune<\/mark> Jew costs"}]},{"docId":"1904-03-22","docUri":"1904-03-22.html","score":2,"contexts":[{"form":"Geniune","weight":"1","pos":2,"context":" The <mark>Geniune<\/mark> Jew "},{"form":"Geniune","weight":"1","pos":5,"context":"The <mark>Geniune<\/mark> Jew costs"}]},{"docId":"1904-03-18","docUri":"1904-03-18.html","score":2,"contexts":[{"form":"Geniune","weight":"1","pos":4,"context":"The <mark>Geniune<\/mark> Jew"},{"form":"Geniune","weight":"1","pos":7,"context":"The <mark>Geniune<\/mark> Jew costs"}]},{"docId":"1904-03-15","docUri":"1904-03-15.html","score":2,"contexts":[{"form":"Geniune","weight":"1","pos":4,"context":" The <mark>Geniune<\/mark> Jew "},{"form":"Geniune","weight":"1","pos":16,"context":"The <mark>Geniune<\/mark> Jew costs"}]},{"docId":"1904-03-01","docUri":"1904-03-01.html","score":2,"contexts":[{"form":"Geniune","weight":"1","pos":4,"context":"The <mark>Geniune<\/mark> Jew"},{"form":"Geniune","weight":"1","pos":16,"context":"The <mark>Geniune<\/mark> Jew costs"}]},{"docId":"1904-03-04","docUri":"1904-03-04.html","score":2,"contexts":[{"form":"Geniune","weight":"1","pos":4,"context":"The <mark>Geniune<\/mark> Jew"},{"form":"Geniune","weight":"1","pos":16,"context":"The <mark>Geniune<\/mark> Jew costs"}]},{"docId":"1904-03-11","docUri":"1904-03-11.html","score":2,"contexts":[{"form":"Geniune","weight":"1","pos":2,"context":" The <mark>Geniune<\/mark> Jew "},{"form":"Geniune","weight":"1","pos":5,"context":"The <mark>Geniune<\/mark> Jew costs"}]},{"docId":"1904-02-26","docUri":"1904-02-26.html","score":1,"contexts":[{"form":"Geniune","weight":"1","pos":4,"context":"The <mark>Geniune<\/mark> Jew"}]},{"docId":"1904-03-25","docUri":"1904-03-25.html","score":1,"contexts":[{"form":"Geniune","weight":"1","pos":7,"context":"The <mark>Geniune<\/mark> Jew costs"}]},{"docId":"1904-02-19","docUri":"1904-02-19.html","score":1,"contexts":[{"form":"Geniune","weight":"1","pos":16,"context":"The <mark>Geniune<\/mark> Jew costs"}]}]}