{"stem":"genuin","instances":[{"docId":"1904-02-19","docUri":"1904-02-19.html","score":3,"contexts":[{"form":"Genuine","weight":"1","pos":63,"context":"...\"Der wahre Jude\",Lviv, Sonnengasse 27 The <mark>Genuine<\/mark> Jew is published every Friday Lemberg, den 19....","fid":"p__14"},{"form":"genuine","weight":"1","pos":306,"context":"..., a great scholar, a gaon, a <mark>genuine<\/mark> pious Jews, who should devote himself to the...","fid":"p__4"},{"form":"genuine","weight":"1","pos":614,"context":"...need to describe the damage this causes against the <mark>genuine<\/mark> Jewry and the dignity of the Torah. Every...","fid":"p__6"}]},{"docId":"1904-02-05","docUri":"1904-02-05.html","score":1,"contexts":[{"form":"Genuine","weight":"1","pos":65,"context":"...\"Der wahre Jude\",Lviv, Sonnengasse 27 The <mark>Genuine<\/mark> Jew is published every Friday Lemberg, den 5....","fid":"p__14"}]},{"docId":"1904-02-12","docUri":"1904-02-12.html","score":1,"contexts":[{"form":"Genuine","weight":"1","pos":63,"context":"...\"Der Wahre Jude\",Lviv, Sonnengasse 27 The <mark>Genuine<\/mark> Jew is published every Friday. Lemberg, den...","fid":"p__14"}]}]}