{"stem":"germani","instances":[{"docId":"1904-02-12","docUri":"1904-02-12.html","score":5,"contexts":[{"form":"Germany","weight":"1","pos":2048,"context":"...will certainly not watch from afar. Then, <mark>Germany<\/mark> and Italy also need to intervene, therefore developing...","fid":"p__12"},{"form":"Germany","weight":"1","pos":3299,"context":"...all of Korea, but the allied powers of <mark>Germany<\/mark>, Russia, and France interfered and forced Japan...","fid":"p__9"},{"form":"Germany","weight":"1","pos":4346,"context":"...and happened in the old city of Rothenburg in <mark>Germany<\/mark>. In the thirteenth century - according to the..."},{"form":"Germany","weight":"1","pos":4396,"context":"...emperor [Frederick II] - the ruler of <mark>Germany<\/mark> at that time. The German peoples were dissatisfied...","fid":"p__10"},{"form":"Germany","weight":"1","pos":4549,"context":".... He was well-known in all of <mark>Germany<\/mark>, from all sides he was asked questions to..."}]},{"docId":"1904-02-05","docUri":"1904-02-05.html","score":4,"contexts":[{"form":"Germany","weight":"1","pos":1899,"context":"...be found in America, in Hungary, in <mark>Germany<\/mark>, in England, the Polish and the Galician..."},{"form":"Germany","weight":"1","pos":4514,"context":"...allows the Russian secret police to be stationed in <mark>Germany<\/mark> and spy out and denounce Russian Jewish people who..."},{"form":"Germany","weight":"1","pos":4525,"context":"...out and denounce Russian Jewish people who migrated to <mark>Germany<\/mark>. "},{"form":"Germany","weight":"1","pos":5047,"context":"...In his youth, Rashi went to Mainz (<mark>Germany<\/mark>) where at that time was an important rabbinical..."}]}]}