{"stem":"half","instances":[{"docId":"1904-02-12","docUri":"1904-02-12.html","score":6,"contexts":[{"form":"half","weight":"1","pos":32,"context":"For a <mark>half<\/mark> year - 4 \"","fid":"div__31"},{"form":"half","weight":"1","pos":35,"context":"For a <mark>half<\/mark> year - 6 \"","fid":"div__31"},{"form":"half","weight":"1","pos":1264,"context":"...chancellery of Orthodox Jews in Budapest that he meets <mark>half<\/mark> of their demands. That means: he issued...","fid":"p__7"},{"form":"half","weight":"1","pos":2445,"context":"...as won to the benefit of Japan. Over <mark>half<\/mark> of the Russian ships which are in East Asia...","fid":"p__5"},{"form":"half","weight":"1","pos":2464,"context":"...least have been incapacitated. Part of the other <mark>half<\/mark> are in the port of Vladivostok which is frozen...","fid":"p__5"},{"form":"half","weight":"1","pos":3207,"context":".... Those inhabitants are great fanatics, lazy, <mark>half<\/mark>-asleep and live like their ancestors a hundred...","fid":"p__9"}]},{"docId":"1904-02-05","docUri":"1904-02-05.html","score":4,"contexts":[{"form":"half","weight":"1","pos":32,"context":"For a <mark>half<\/mark> year - 4 \"","fid":"div__31"},{"form":"half","weight":"1","pos":35,"context":"For a <mark>half<\/mark> year - 6 \"","fid":"div__31"},{"form":"half","weight":"1","pos":431,"context":"For a <mark>half<\/mark> year - 4\"","fid":"div__23"},{"form":"half","weight":"1","pos":443,"context":" Those who send the money at least <mark>half<\/mark> a year in advance will get an important Jewish...","fid":"p__8"}]}]}