{"stem":"heaven","instances":[{"docId":"1904-02-12","docUri":"1904-02-12.html","score":1,"contexts":[{"form":"heaven","weight":"1","pos":4989,"context":"...slander is now believed by the mobs, then <mark>heaven<\/mark> help us, massive hardship will come over Jewish people..."}]},{"docId":"1904-03-29","docUri":"1904-03-29.html","score":1,"contexts":[{"form":"heaven","weight":"1","pos":4222,"context":"...they shed an ocean of tears for God in <mark>heaven<\/mark>. The father swore a holy oath with the..."}]},{"docId":"1904-03-08","docUri":"1904-03-08.html","score":1,"contexts":[{"form":"heaven","weight":"1","pos":823,"context":"...will flourish anew, and justice will descend from <mark>heaven<\/mark>. "}]},{"docId":"1904-03-25","docUri":"1904-03-25.html","score":1,"contexts":[{"form":"Heaven","weight":"1","pos":1441,"context":"...to be honest and pious Jews, good for <mark>Heaven<\/mark> and Creation, good for God and for the..."}]},{"docId":"1904-02-26","docUri":"1904-02-26.html","score":1,"contexts":[{"form":"heavens","weight":"1","pos":3408,"context":"...quote seems to come true: \"Also from the <mark>heavens<\/mark> the stars fought from their courses\". - The..."}]},{"docId":"1904-02-19","docUri":"1904-02-19.html","score":1,"contexts":[{"form":"heaven","weight":"1","pos":1171,"context":".... He prematurely promises, how one says, <mark>heaven<\/mark> and earth. He is talking about new military..."}]}]}