{"stem":"hors","instances":[{"docId":"1904-02-05","docUri":"1904-02-05.html","score":4,"contexts":[{"form":"horses","weight":"1","pos":5286,"context":"...him away and he will return home with three <mark>horses<\/mark> only. In the end, it happened like...","fid":"p__23"},{"form":"horses","weight":"1","pos":5303,"context":"...only difference being that Godfrey came back with four <mark>horses<\/mark>. He wanted to punish Rashi, because his...","fid":"p__23"},{"form":"horses","weight":"1","pos":5317,"context":"...completely fulfilled, as he came back with four <mark>horses<\/mark>. However, as he arrived at the city...","fid":"p__23"},{"form":"horse","weight":"1","pos":5330,"context":"...gates, the gate suddenly fell and squashed one <mark>horse<\/mark>. Therefore, Rashi`s prophecy came completely true...","fid":"p__23"}]},{"docId":"1904-03-04","docUri":"1904-03-04.html","score":2,"contexts":[{"form":"horse","weight":"1","pos":5150,"context":"...stuck in his kerchief without hurting him. His <mark>horse<\/mark> was shot, but he quickly obtained another horse...","fid":"p__24"},{"form":"horse","weight":"1","pos":5156,"context":"...horse was shot, but he quickly obtained another <mark>horse<\/mark> and threw himself into battle again with even more...","fid":"p__24"}]},{"docId":"1904-02-19","docUri":"1904-02-19.html","score":1,"contexts":[{"form":"horses","weight":"1","pos":4037,"context":"...“Kabyle people” (wild Arabs) came riding on <mark>horses<\/mark> and destroyed the Jewish quarters. They plundered and...","fid":"p__6"}]},{"docId":"1904-03-25","docUri":"1904-03-25.html","score":1,"contexts":[{"form":"horses","weight":"1","pos":2923,"context":"...antisemites chevy Jews again by claiming that they sell <mark>horses<\/mark> for the Japanese. ","fid":"p__7"}]},{"docId":"1904-02-26","docUri":"1904-02-26.html","score":1,"contexts":[{"form":"horses","weight":"1","pos":3963,"context":"...The cavalry has also received orders to prepare their <mark>horses<\/mark> - even the sick ones who have been handed...","fid":"p__8"}]}]}