{"stem":"jew","instances":[{"docId":"1904-02-19","docUri":"1904-02-19.html","score":30,"contexts":[{"form":"jew","weight":"1","pos":7,"context":" The Geniune <mark>jew<\/mark>    ","fid":"div__7"},{"form":"Jew","weight":"1","pos":19,"context":"   The Geniune <mark>Jew<\/mark> costs                     ","fid":"div__31"},{"form":"Jew","weight":"1","pos":66,"context":"...wahre Jude\",Lviv, Sonnengasse 27 The Genuine <mark>Jew<\/mark> is published every Friday Lemberg, den 19. Februar...","fid":"p__14"},{"form":"Jew","weight":"1","pos":250,"context":"..., a scholar, a gaon, a pious <mark>Jew<\/mark>, who works with the Torah all day....","fid":"p__6"},{"form":"Jews","weight":"1","pos":310,"context":"...great scholar, a gaon, a genuine pious <mark>Jews<\/mark>, who should devote himself to the Jewry and...","fid":"p__4"},{"form":"Jews","weight":"1","pos":374,"context":"..., our representatives in the imperial council are progressive <mark>Jews<\/mark>. They only wanted rabbis who can hold beautiful...","fid":"p__4"},{"form":"Jews’","weight":"1","pos":424,"context":"...has to admit that the government understood the pious <mark>Jews’<\/mark> interests better and brought more ease against the will...","fid":"p__5"},{"form":"Jews","weight":"1","pos":512,"context":"..., the government makes every possible facilitation for pious <mark>Jews<\/mark>. ","fid":"p__5"},{"form":"Jews","weight":"1","pos":578,"context":"...not have diplomas. Who knows if the progressive <mark>Jews<\/mark> who are superintendents in most communities, will allow...","fid":"p__6"},{"form":"Jews","weight":"1","pos":590,"context":"...allow another petition - against the will of pious <mark>Jews<\/mark> - a “doctrine” for rabbis as it had already...","fid":"p__6"},{"form":"Jew","weight":"1","pos":625,"context":"...and the dignity of the Torah. Every pious <mark>Jew<\/mark> knows and senses that the Jewish rabbis lose their...","fid":"p__6"},{"form":"Jews","weight":"1","pos":648,"context":"...who are tolerated out of pity. The pious <mark>Jews<\/mark> are the ones who mostly care about the communities...","fid":"p__6"},{"form":"Jews","weight":"1","pos":683,"context":"...for ritual immersion and the like (which progressive <mark>Jews<\/mark> do not use nor need), now have to...","fid":"p__6"},{"form":"Jews","weight":"1","pos":2345,"context":"...have already amassed over 25 million crowns. American <mark>Jews<\/mark> are buying a battleship at their own expense,...","fid":"p__7"},{"form":"Jews","weight":"1","pos":3438,"context":"...the whole world is interested in Japan and whether <mark>Jews<\/mark> are living there. According to the latest reports...","fid":"p__11"},{"form":"Jews","weight":"1","pos":3448,"context":"...there. According to the latest reports around 100 <mark>Jews<\/mark> are living there. Twenty Jewish families live in...","fid":"p__11"},{"form":"Jews","weight":"1","pos":3489,"context":"...In Japan, there is freedom of religion and <mark>Jews<\/mark> are equal with every citizen in the country....","fid":"p__11"},{"form":"Jews","weight":"1","pos":3498,"context":"...with every citizen in the country. - Few <mark>Jews<\/mark> live in Korea, the country Japan is waging...","fid":"p__11"},{"form":"Jew","weight":"1","pos":3511,"context":"...against Russia for. A few years ago a <mark>Jew<\/mark> operated a European restaurant in the capital Seoul;...","fid":"p__11"},{"form":"Jew","weight":"1","pos":3572,"context":"...adapting to Christian customs and culture). - The <mark>Jew<\/mark> Elijah Hift in Berehove inherited 300 million. His...","fid":"p__10"},{"form":"Jews","weight":"1","pos":3679,"context":"...way and some were beaten. Therefore, the <mark>Jews<\/mark> filed a suit but the judges wanted to release...","fid":"p__8"},{"form":"Jews","weight":"1","pos":3801,"context":"...subsided a bit. Then 1903, again 8011 <mark>Jews<\/mark> emigrated from Romania. ","fid":"p__10"},{"form":"Jews","weight":"1","pos":3823,"context":"...But not only workers or mobs bear grudges against <mark>Jews<\/mark>, but higher classes now as well. For...","fid":"p__13"},{"form":"Jews","weight":"1","pos":3940,"context":"...these clauses are directed against Jewish people. Unfortunate <mark>Jews<\/mark> are persecuted like this in the whole world....","fid":"p__13"},{"form":"Jews","weight":"1","pos":3992,"context":" New details to the horrible persecution against <mark>Jews<\/mark> in Morocco, which we have reported on in...","fid":"p__8"},{"form":"Jews","weight":"1","pos":4060,"context":"...and took several women and children captive. Two <mark>Jews<\/mark> have been trampled to death, children and women...","fid":"p__8"},{"form":"Jews","weight":"1","pos":4107,"context":"...foods have been stolen almost everywhere. The unlucky <mark>Jews<\/mark> have fled into all directions; nobody knew where...","fid":"p__8"},{"form":"Jews","weight":"1","pos":4151,"context":"...to be benevolent. They took in many eloping <mark>Jews<\/mark> in their homes. One of them rode out...","fid":"p__8"},{"form":"Jews","weight":"1","pos":4184,"context":".... - In the city Marrakech, where 14,000 <mark>Jews<\/mark> reside, persecution has been reported as well....","fid":"p__8"},{"form":"Jews","weight":"1","pos":4257,"context":"...communities, the governments supporting them. Not only <mark>Jews<\/mark>, but also Christians used to come and whatever...","fid":"p__3"}]},{"docId":"1904-02-05","docUri":"1904-02-05.html","score":18,"contexts":[{"form":"jew","weight":"1","pos":7,"context":" The Geniune <mark>jew<\/mark>    ","fid":"div__6"},{"form":"Jew","weight":"1","pos":19,"context":"   The Geniune <mark>Jew<\/mark> costs                     ","fid":"div__31"},{"form":"Jew","weight":"1","pos":66,"context":"...wahre Jude\",Lviv, Sonnengasse 27 The Genuine <mark>Jew<\/mark> is published every Friday Lemberg, den 5. Februar...","fid":"p__14"},{"form":"Jew","weight":"1","pos":75,"context":" The Geniune <mark>Jew<\/mark>      ","fid":"div__12"},{"form":"Jew\"","weight":"1","pos":85,"context":"\"The Geniune <mark>Jew\"<\/mark>","fid":"p__5"},{"form":"Jew","weight":"1","pos":139,"context":"...well as general world news. Therefore, every <mark>Jew<\/mark> will find in our paper a short but detailed...","fid":"p__6"},{"form":"Jew\"","weight":"1","pos":281,"context":" \"The Geniune <mark>Jew\"<\/mark>. ","fid":"p__8"},{"form":"Jew\"","weight":"1","pos":426,"context":"    \"The Geniune <mark>Jew\"<\/mark> costs             ","fid":"div__23"},{"form":"Jew”","weight":"1","pos":587,"context":"...by another class of writers, and “The Geniune <mark>Jew”<\/mark> on the other hand will be in another manner...","fid":"p__7"},{"form":"Jew","weight":"1","pos":614,"context":"...to the program will be paper for the common <mark>Jew<\/mark>, it will publish articles from good writers,...","fid":"p__7"},{"form":"Jew”","weight":"1","pos":846,"context":"...who hopefully will understand the value of the “Geniune <mark>Jew”<\/mark>. ","fid":"p__8"},{"form":"Jew","weight":"1","pos":1277,"context":"...this? We have to admit: the common <mark>Jew<\/mark>, the pious are also not completely free of...","fid":"p__6"},{"form":"Jew","weight":"1","pos":1476,"context":"...return the crown back to the Torah! A <mark>Jew<\/mark> ","fid":"p__11"},{"form":"Jew","weight":"1","pos":1713,"context":"...many and nowadays it is very hard for a <mark>Jew<\/mark> to become a public official, even a small...","fid":"p__5"},{"form":"Jew","weight":"1","pos":1734,"context":"...that, because a merchant can continue being a <mark>Jew<\/mark>, like a “doctor” or a “public official”....","fid":"p__5"},{"form":"Jew’s","weight":"1","pos":2776,"context":"...that several provinces are in favour of expanding the <mark>Jew’s<\/mark> rights to live in Russia as they cannot watch...","fid":"p__13"},{"form":"Jew","weight":"1","pos":4487,"context":".... He was a great philanthropist and a pious <mark>Jew<\/mark>. May his memory be a blessing. -...","fid":"p__13"},{"form":"Jew","weight":"1","pos":4906,"context":"...died. The name has well known to every <mark>Jew<\/mark>, every schoolboy knows him and also the biggest...","fid":"p__7"}]},{"docId":"1904-02-12","docUri":"1904-02-12.html","score":8,"contexts":[{"form":"jew","weight":"1","pos":7,"context":" The Geniune <mark>jew<\/mark>    ","fid":"div__7"},{"form":"Jew","weight":"1","pos":19,"context":"   The Geniune <mark>Jew<\/mark> costs                     ","fid":"div__31"},{"form":"Jew","weight":"1","pos":66,"context":"...Wahre Jude\",Lviv, Sonnengasse 27 The Genuine <mark>Jew<\/mark> is published every Friday. Lemberg, den 12....","fid":"p__14"},{"form":"Jews","weight":"1","pos":860,"context":" The Hungarian <mark>Jews<\/mark>, their lives, their political and economical situation...","fid":"p__2"},{"form":"Jew","weight":"1","pos":877,"context":"...really known to our Jewish readers. The Hungarian <mark>Jew<\/mark> is a different “type”, he differs from the...","fid":"p__2"},{"form":"Jew","weight":"1","pos":925,"context":"...want to share important information which will interest every <mark>Jew<\/mark>. ","fid":"p__2"},{"form":"Jews","weight":"1","pos":1262,"context":"...week he gave confirmation to the chancellery of Orthodox <mark>Jews<\/mark> in Budapest that he meets half of their demands...","fid":"p__7"},{"form":"Jews","weight":"1","pos":4856,"context":"...fears. I think the good times for us <mark>Jews<\/mark> in Rothenburg are over and tough, sad days...","fid":"p__15"}]}]}