{"stem":"kept","instances":[{"docId":"1904-02-19","docUri":"1904-02-19.html","score":2,"contexts":[{"form":"kept","weight":"1","pos":2682,"context":"...land will take place. The Japanese movements are <mark>kept<\/mark> in secret and it is not known where they...","fid":"p__15"},{"form":"kept","weight":"1","pos":4503,"context":"...into Meir’s heart like arrows. But he <mark>kept<\/mark> calm and said “For God I may kneel and...","fid":"p__12"}]},{"docId":"1904-03-29","docUri":"1904-03-29.html","score":1,"contexts":[{"form":"kept","weight":"1","pos":1448,"context":"...In the Hungarian parliament meanwhile peace and quiet is <mark>kept<\/mark>; several important laws have been passed. It...","fid":"p__7"}]},{"docId":"1904-03-01","docUri":"1904-03-01.html","score":1,"contexts":[{"form":"kept","weight":"1","pos":1185,"context":"...Furthermore, both countries agreed to keep order and <mark>kept<\/mark> the Balkan countries to wage war with Turkey because...","fid":"p__36"}]},{"docId":"1904-03-08","docUri":"1904-03-08.html","score":1,"contexts":[{"form":"kept","weight":"1","pos":653,"context":"...Clam, who led the trial against Dreyfus, <mark>kept<\/mark> all documents which proved Dreyfus’ innocence and did...","fid":"p__10"}]}]}