{"stem":"kilogram","instances":[{"docId":"1904-03-15","docUri":"1904-03-15.html","score":3,"contexts":[{"form":"kilogram","weight":"1","pos":1495,"context":"...crown, one litre petroleum 80 heller, one <mark>kilogram<\/mark> potatoes 20 heller, one kilogram bread 45 heller...","fid":"p__4"},{"form":"kilogram","weight":"1","pos":1499,"context":"...heller, one kilogram potatoes 20 heller, one <mark>kilogram<\/mark> bread 45 heller. Other cities are even more...","fid":"p__4"},{"form":"kilograms","weight":"1","pos":1583,"context":"...in the city hall that the administration bought 6,000 <mark>kilograms<\/mark> of bread and will sell them cheaply. They...","fid":"p__5"}]},{"docId":"1904-02-19","docUri":"1904-02-19.html","score":1,"contexts":[{"form":"kilogram","weight":"1","pos":5129,"context":"The best varieties are sent in 5 <mark>kilogram<\/mark> packages prepaid against sending details, the rest payment...","fid":"p__5"}]},{"docId":"1904-02-05","docUri":"1904-02-05.html","score":1,"contexts":[{"form":"kilogram","weight":"1","pos":5609,"context":" The best varieties are sent in 5 <mark>kilogram<\/mark> packages prepaid against sending details, the rest payment...","fid":"p__3"}]}]}