{"stem":"less","instances":[{"docId":"1904-02-05","docUri":"1904-02-05.html","score":3,"contexts":[{"form":"less","weight":"1","pos":2095,"context":"...the children raised in a Jewish manner are becoming <mark>less<\/mark> and less. Also pious, honest parents sometimes...","fid":"p__5"},{"form":"less","weight":"1","pos":2097,"context":"...raised in a Jewish manner are becoming less and <mark>less<\/mark>. Also pious, honest parents sometimes don’t care...","fid":"p__5"},{"form":"less","weight":"1","pos":5577,"context":" Also <mark>less<\/mark> than 5 kg, payment on delivery, prepaid,...","fid":"p__2"}]}]}