{"stem":"lie","instances":[{"docId":"1904-03-08","docUri":"1904-03-08.html","score":6,"contexts":[{"form":"lie","weight":"1","pos":169,"context":".... It is possible that the falsehood, the <mark>lie<\/mark>, can win for a short time, but...","fid":"p__3"},{"form":"lies","weight":"1","pos":194,"context":"...It is horrible to think about the heap of <mark>lies<\/mark> and duplicity which the French generals pinned on poor...","fid":"p__10"},{"form":"lie","weight":"1","pos":220,"context":"...to be a fairy tale which is a preposterous <mark>lie<\/mark>. Nobody will believe that something like this is...","fid":"p__10"},{"form":"lies","weight":"1","pos":242,"context":"...is still not the whole story. Deceptions and <mark>lies<\/mark> that have not been uncovered yet are still present...","fid":"p__10"},{"form":"lies","weight":"1","pos":338,"context":"...is how great the power of deception is; of <mark>lies<\/mark>, of violence, of persecution and of antisemitism...","fid":"p__10"},{"form":"lie","weight":"1","pos":735,"context":"...This investigation will last several more months. Every <mark>lie<\/mark>, every contortion will be exposed and in the...","fid":"p__8"}]},{"docId":"1904-03-11","docUri":"1904-03-11.html","score":3,"contexts":[{"form":"lies","weight":"1","pos":833,"context":"...school of Kishinev, everything is broken, There <mark>lies<\/mark> the beadle of Rabbi Moshe, violence and fear...","fid":"p__14"},{"form":"lies","weight":"1","pos":841,"context":"...of Rabbi Moshe, violence and fear! He <mark>lies<\/mark> in a pool of blood, beaten to death...","fid":"p__14"},{"form":"lying","weight":"1","pos":2449,"context":"...They look around and find a familiar travelling citizen <mark>lying<\/mark> in the bed and ripping her hair out....","fid":"p__10"}]},{"docId":"1904-03-18","docUri":"1904-03-18.html","score":2,"contexts":[{"form":"lies","weight":"1","pos":742,"context":"...for Passover, to refresh the old, foolish <mark>lies<\/mark> of ritual murders. No explanation or proof is...","fid":"p__4"},{"form":"lying","weight":"1","pos":3455,"context":"..., screeching seven times in “summer”. An ox <mark>lying<\/mark> down on his knees symbolises “autumn” and “winter” is...","fid":"p__10"}]},{"docId":"1904-02-12","docUri":"1904-02-12.html","score":2,"contexts":[{"form":"lied","weight":"1","pos":424,"context":"...goes back to school and explains that the teacher <mark>lied<\/mark> about Chametz not being forbidden to eat .The...","fid":"p__7"},{"form":"lies","weight":"1","pos":583,"context":"...telling fairy tales, that we are suspected of <mark>lies<\/mark>. We want to bring facts which have been...","fid":"p__12"}]},{"docId":"1904-02-19","docUri":"1904-02-19.html","score":1,"contexts":[{"form":"lying","weight":"1","pos":2760,"context":"...But as everyone knows, the Russian reports are <mark>lying<\/mark>; nobody believes them. Meanwhile, Russia is...","fid":"p__15"}]},{"docId":"1904-02-26","docUri":"1904-02-26.html","score":1,"contexts":[{"form":"lies","weight":"1","pos":1621,"context":"...truth. Unfortunately, these times are filled with <mark>lies<\/mark> and the truth hides in the corner, it...","fid":"p__3"}]}]}