{"stem":"men","instances":[{"docId":"1904-02-05","docUri":"1904-02-05.html","score":1,"contexts":[{"form":"men","weight":"1","pos":92,"context":"...biographies of rabbi. Gaon and other big Jewish <mark>men<\/mark> which have advocated for on behalf of the community..."}]},{"docId":"1904-03-04","docUri":"1904-03-04.html","score":1,"contexts":[{"form":"men","weight":"1","pos":103,"context":"...Great has been defeated with an army of 80,000 <mark>men<\/mark> against a small army with a brave king.)..."}]}]}