{"stem":"peculiar","instances":[{"docId":"1904-03-18","docUri":"1904-03-18.html","score":2,"contexts":[{"form":"peculiar","weight":"1","pos":3205,"context":" (A <mark>peculiar<\/mark> clock hand). Not long ago, a poor...","fid":"p__10"},{"form":"peculiar","weight":"1","pos":3228,"context":"...and it is viewed as one of the more <mark>peculiar<\/mark> things. The hand is encased in a glass...","fid":"p__10"}]},{"docId":"1904-03-08","docUri":"1904-03-08.html","score":1,"contexts":[{"form":"peculiar","weight":"1","pos":1262,"context":"...Hungary has been separated from Austria and forms a <mark>peculiar<\/mark> country. It has its own ministry, a...","fid":"p__19"}]},{"docId":"1904-03-22","docUri":"1904-03-22.html","score":1,"contexts":[{"form":"peculiar","weight":"1","pos":1424,"context":"..., all the tasks are carried out with a <mark>peculiar<\/mark> dexterity and swiftness and those animals never shy away...","fid":"p__4"}]}]}