{"stem":"pure","instances":[{"docId":"1904-03-25","docUri":"1904-03-25.html","score":3,"contexts":[{"form":"pure","weight":"1","pos":1633,"context":"...which they need to provide for the young and <mark>pure<\/mark> child’s heart. They should plant love for the..."},{"form":"pure","weight":"1","pos":5405,"context":" If you want to drink <mark>pure<\/mark>, unadulterated tea, write to the address below..."},{"form":"pure","weight":"1","pos":5413,"context":"...to the address below, 1 kg fine, <mark>pure<\/mark> tea only 6 crowns. There is also tea..."}]},{"docId":"1904-03-18","docUri":"1904-03-18.html","score":3,"contexts":[{"form":"pure","weight":"1","pos":3570,"context":"...water. Papyrus likes shallow, still, and <mark>pure<\/mark> water. Its roots are thin and soft,..."},{"form":"pure","weight":"1","pos":4645,"context":" If you want to drink <mark>pure<\/mark>, unadulterated tea, write to the address below..."},{"form":"pure","weight":"1","pos":4653,"context":"...to the address below, 1 kg fine, <mark>pure<\/mark> tea only 6 crowns. There is also tea..."}]},{"docId":"1904-02-12","docUri":"1904-02-12.html","score":2,"contexts":[{"form":"pure","weight":"1","pos":5253,"context":" If you want to drink <mark>pure<\/mark>, unadulterated tea, write to the address below..."},{"form":"pure","weight":"1","pos":5261,"context":"...to the address below, 1 kg fine, <mark>pure<\/mark> tea only 6 crowns. There is also tea..."}]},{"docId":"1904-03-29","docUri":"1904-03-29.html","score":2,"contexts":[{"form":"pure","weight":"1","pos":5503,"context":" If you want to drink <mark>pure<\/mark>, unadulterated tea, write to the address below..."},{"form":"pure","weight":"1","pos":5511,"context":"...to the address below, 1 kg fine, <mark>pure<\/mark> tea only 6 crowns. There is also tea..."}]},{"docId":"1904-03-11","docUri":"1904-03-11.html","score":2,"contexts":[{"form":"pure","weight":"1","pos":4812,"context":" If you want to drink <mark>pure<\/mark>, unadulterated tea, write to the address below..."},{"form":"pure","weight":"1","pos":4820,"context":"...to the address below, 1 kg fine, <mark>pure<\/mark> tea only 6 crowns. There is also tea..."}]},{"docId":"1904-02-26","docUri":"1904-02-26.html","score":2,"contexts":[{"form":"pure","weight":"1","pos":4671,"context":" If you want to drink <mark>pure<\/mark>, unadulterated tea, write to the address below..."},{"form":"pure","weight":"1","pos":4679,"context":"...to the address below, 1 kg fine, <mark>pure<\/mark> tea only 6 crowns. There is also tea..."}]},{"docId":"1904-02-19","docUri":"1904-02-19.html","score":2,"contexts":[{"form":"pure","weight":"1","pos":4862,"context":" If you want to drink <mark>pure<\/mark>, unadulterated tea, write to the address below..."},{"form":"pure","weight":"1","pos":4870,"context":"...to the address below, 1 kg fine, <mark>pure<\/mark> tea only 6 crowns. There is also tea..."}]}]}