{"stem":"rovereto","instances":[{"docId":"1904-03-18","docUri":"1904-03-18.html","score":1,"contexts":[{"form":"Rovereto","weight":"1","pos":1368,"context":"...by which an Italian university shall be built in <mark>Rovereto<\/mark>, Tyrol. The government chose this city especially...","fid":"p__17"}]},{"docId":"1904-03-11","docUri":"1904-03-11.html","score":1,"contexts":[{"form":"Rovereto","weight":"1","pos":1995,"context":"...build an Italian university in the Tyrolean city of <mark>Rovereto<\/mark> and called upon the parliament to finally get to...","fid":"p__9"}]}]}