{"stem":"samuel","instances":[{"docId":"1904-02-05","docUri":"1904-02-05.html","score":3,"contexts":[{"form":"Samuel","weight":"1","pos":4467,"context":" (Berlin). The well known benefactor <mark>Samuel<\/mark> Straus died in Karlsruhe. He was a great..."},{"form":"Samuel","weight":"1","pos":5388,"context":"...Rashi’s sons in law, Rabbi Meir ben <mark>Samuel<\/mark>, had three famous sons: Rabbi Samuel ben..."},{"form":"Samuel","weight":"1","pos":5394,"context":"...ben Samuel, had three famous sons: Rabbi <mark>Samuel<\/mark> ben Meir (known as RaShbaM),Rabbi Isaac..."}]}]}