{"stem":"side","instances":[{"docId":"1904-03-11","docUri":"1904-03-11.html","score":8,"contexts":[{"form":"side","weight":"1","pos":783,"context":"...the destroyed school in Chișinău, pictured from one <mark>side<\/mark>, the beadle of Rabbi Moshe lays in blood...","fid":"p__4"},{"form":"side","weight":"1","pos":797,"context":"...holds a torn Torah scroll. On the other <mark>side<\/mark> is the harbour of Port Arthur with destroyed battleships...","fid":"p__4"},{"form":"side","weight":"1","pos":1015,"context":" Lately we are being suppressed from every <mark>side<\/mark>, meeting our needs has become difficult or it...","fid":"p__4"},{"form":"side","weight":"1","pos":1050,"context":"...on. The number of antisemites grow continuously to every <mark>side<\/mark>, their wants do as well. They do...","fid":"p__4"},{"form":"side","weight":"1","pos":2469,"context":"...waved them over. As they were on her <mark>side<\/mark>, the woman poured out her heart. She...","fid":"p__10"},{"form":"side","weight":"1","pos":3242,"context":"...this is not possible. Japan on the other <mark>side<\/mark> is not far away from its country and can...","fid":"p__11"},{"form":"side","weight":"1","pos":3460,"context":"...managed to dispose of the military on the landward <mark>side<\/mark> of Vladivostok. It will soon besiege the fortress...","fid":"p__19"},{"form":"sides","weight":"1","pos":3468,"context":".... It will soon besiege the fortress from all <mark>sides<\/mark>. ","fid":"p__19"}]},{"docId":"1904-03-18","docUri":"1904-03-18.html","score":7,"contexts":[{"form":"side","weight":"1","pos":3342,"context":"...hour is announced by an angel on the left <mark>side<\/mark> of the field. Two angles strike the quarter...","fid":"p__10"},{"form":"side","weight":"1","pos":3367,"context":"...the four ages of humans. On the right <mark>side<\/mark> the angel of death appears killing with his sword...","fid":"p__10"},{"form":"side","weight":"1","pos":3404,"context":"...the same time an angel appears from the right <mark>side<\/mark> and blows a trumpet. Allegorical figures are situated...","fid":"p__10"},{"form":"side","weight":"1","pos":3419,"context":"...roof, symbolising the seasons. On the left <mark>side<\/mark> is a rooster which starts flapping, craning its...","fid":"p__10"},{"form":"side","weight":"1","pos":3450,"context":"...cuckoo from above and a quail from the left <mark>side<\/mark>, screeching seven times in “summer”. An ox...","fid":"p__10"},{"form":"side","weight":"1","pos":3793,"context":"...on it and as the writing goes on, one <mark>side<\/mark> of the papyrus is rolled in further while the...","fid":"p__5"},{"form":"side","weight":"1","pos":3801,"context":"...the papyrus is rolled in further while the other <mark>side<\/mark> is unraveled. It is non-profitable to...","fid":"p__5"}]},{"docId":"1904-02-12","docUri":"1904-02-12.html","score":5,"contexts":[{"form":"side","weight":"1","pos":2017,"context":"...Manchuria. Japan has England and America on their <mark>side<\/mark>, as Japan is waging war for them as...","fid":"p__38"},{"form":"side","weight":"1","pos":2804,"context":"...That is how the first message from the war <mark>side<\/mark> is written. One could imagine that if the...","fid":"p__10"},{"form":"side","weight":"1","pos":3559,"context":"...for war in Asia. Japan on the other <mark>side<\/mark>, also braced themselves for war. After a while...","fid":"p__19"},{"form":"sides","weight":"1","pos":4541,"context":"...-known in all of Germany, from all <mark>sides<\/mark> he was asked questions to receive the answers and...","fid":"p__10"},{"form":"sides","weight":"1","pos":4922,"context":"...locked up and set on fire from all four <mark>sides<\/mark> and all Jewish people have been thrown into the...","fid":"p__19"}]},{"docId":"1904-03-01","docUri":"1904-03-01.html","score":4,"contexts":[{"form":"sides","weight":"1","pos":324,"context":"...shall fall! Russia is being deserted from all <mark>sides<\/mark>, all its Asian neighbours, which used to...","fid":"p__21"},{"form":"side","weight":"1","pos":567,"context":"...talked about a lot again lately; about which <mark>side<\/mark> Austria-Hungary will take in case a war...","fid":"p__31"},{"form":"side","weight":"1","pos":928,"context":"...new Slavs Austria would gain come from the Austrian <mark>side<\/mark>, not the Hungarian one, like the Balkan...","fid":"p__14"},{"form":"sides","weight":"1","pos":1359,"context":"...not want Italy to be its neighbour on all <mark>sides<\/mark>. But the","fid":"p__20"}]},{"docId":"1904-02-19","docUri":"1904-02-19.html","score":4,"contexts":[{"form":"sides","weight":"1","pos":1884,"context":"...bought 10,000 rifles and guns. Volunteers from all <mark>sides<\/mark> are gathering who want to join this national-...","fid":"p__21"},{"form":"sides","weight":"1","pos":2559,"context":"...and want to attack the Russian military from both <mark>sides<\/mark>. ","fid":"p__15"},{"form":"sides","weight":"1","pos":3805,"context":"...Antisemitism in England is rising again. From all <mark>sides<\/mark> persecution is reported on. But not only workers or...","fid":"p__13"},{"form":"side","weight":"1","pos":4298,"context":"...the rabbi and two students, one on each <mark>side<\/mark>, followed the attendant - on holidays, two...","fid":"p__6"}]},{"docId":"1904-03-15","docUri":"1904-03-15.html","score":3,"contexts":[{"form":"sides","weight":"1","pos":2169,"context":"...the Japanese. Several dead and wounded on both <mark>sides<\/mark>. ","fid":"p__4"},{"form":"sides","weight":"1","pos":2191,"context":"...Manchuria and Vladivostok. Two divisions march from two <mark>sides<\/mark> onto Vladivostok and the city will soon be trapped...","fid":"p__9"},{"form":"sides","weight":"1","pos":2201,"context":"...and the city will soon be trapped from all <mark>sides<\/mark>. - The Russian battleships in the harbour of...","fid":"p__9"}]},{"docId":"1904-02-05","docUri":"1904-02-05.html","score":1,"contexts":[{"form":"side","weight":"1","pos":3054,"context":"...’s allies, France, also stands on this <mark>side<\/mark>; Russia must be afraid to lose in this...","fid":"p__15"}]},{"docId":"1904-03-04","docUri":"1904-03-04.html","score":1,"contexts":[{"form":"side","weight":"1","pos":1909,"context":"...that and remained silent. The powers on their <mark>side<\/mark> do not bother intermingling with the country’s “inner” affairs...","fid":"p__13"}]},{"docId":"1904-03-25","docUri":"1904-03-25.html","score":1,"contexts":[{"form":"side","weight":"1","pos":3142,"context":"...to travel around the whole lake on the other <mark>side<\/mark>. ","fid":"p__8"}]}]}