{"stem":"situat","instances":[{"docId":"1904-02-05","docUri":"1904-02-05.html","score":8,"contexts":[{"form":"situations","weight":"1","pos":307,"context":"...reports about the different cities and countries about the <mark>situations<\/mark> of our borthers and everything concerning them. g)...","fid":"p__12"},{"form":"situation","weight":"1","pos":1576,"context":"...attention to the question how to improve the financial <mark>situation<\/mark>. A Bat Kol has been shared: “let’s...","fid":"p__5"},{"form":"situation","weight":"1","pos":1729,"context":" The <mark>situation<\/mark> of the Galician Jews is even worse than the...","fid":"p__6"},{"form":"situation","weight":"1","pos":1737,"context":"...of the Galician Jews is even worse than the <mark>situation<\/mark> of other Galician peoples, for they are cared...","fid":"p__6"},{"form":"situation","weight":"1","pos":2865,"context":"...towards them. That is the truth! The <mark>situation<\/mark> of the Russian Jews is indeed very unfortunate,...","fid":"p__9"},{"form":"situated","weight":"1","pos":3269,"context":"...smaller than Austria-Hungary). The Islands are <mark>situated<\/mark> in the corner of East-Asia and border...","fid":"p__12"},{"form":"situation","weight":"1","pos":3851,"context":"...there is not § 14. There, the government’s <mark>situation<\/mark> is a lot more difficult. The new minister...","fid":"p__9"},{"form":"situation","weight":"1","pos":4046,"context":"...and Russia: Recently, the news about the <mark>situation<\/mark> is East Asia has not been clear. Soon...","fid":"p__14"}]}]}