{"stem":"statist","instances":[{"docId":"1904-02-05","docUri":"1904-02-05.html","score":6,"contexts":[{"form":"statistical","weight":"1","pos":366,"context":"...Important information about new inventions, medical articles, <mark>statistical<\/mark> news and similar whatever interests people."},{"form":"statistics","weight":"1","pos":1078,"context":"...is has been necessary to publish a set of <mark>statistics<\/mark> each time. "},{"form":"statistic","weight":"1","pos":1083,"context":" And thus, a <mark>statistic<\/mark> about the baptised Jewish people in Vienna has been..."},{"form":"statistic","weight":"1","pos":1117,"context":"...namely 313 men and 238 women. In this <mark>statistic<\/mark>, the job and occupation of the baptised Jewish..."},{"form":"statistic","weight":"1","pos":1194,"context":" And this public <mark>statistic<\/mark> has not made a huge impression at all...."},{"form":"Statistical","weight":"1","pos":5456,"context":" <mark>Statistical<\/mark> information. "}]},{"docId":"1904-02-26","docUri":"1904-02-26.html","score":2,"contexts":[{"form":"statistics","weight":"1","pos":2732,"context":" According to these <mark>statistics<\/mark>, one might believe that the Jews in East..."},{"form":"statistical","weight":"1","pos":3882,"context":"...every mountain, every city, important railroads, <mark>statistical<\/mark> information and so on. "}]},{"docId":"1904-03-25","docUri":"1904-03-25.html","score":2,"contexts":[{"form":"statistic","weight":"1","pos":4035,"context":"...of people having been the same height is the <mark>statistic<\/mark> of recruits, although it is only viable for..."},{"form":"statistics","weight":"1","pos":4283,"context":".... However, these only constitute exceptions and the <mark>statistics<\/mark> prove that these reasons do not influence the general..."}]},{"docId":"1904-02-19","docUri":"1904-02-19.html","score":1,"contexts":[{"form":"Statistical","weight":"1","pos":4744,"context":"<mark>Statistical<\/mark> Reports."}]}]}