{"stem":"though","instances":[{"docId":"1904-02-05","docUri":"1904-02-05.html","score":2,"contexts":[{"form":"though","weight":"1","pos":3507,"context":"...is about to wage war against Russia and even <mark>though<\/mark> Russia is bigger, Japan will probably win,...","fid":"p__10"},{"form":"though","weight":"1","pos":3650,"context":"...- The government cannot give way to the Czech <mark>though<\/mark>, because the German wanted to block and it...","fid":"p__12"}]},{"docId":"1904-02-12","docUri":"1904-02-12.html","score":1,"contexts":[{"form":"though","weight":"1","pos":2226,"context":"...not let something bad happen to Greece. Even <mark>though<\/mark> Turkey has won the war, they had to give...","fid":"p__22"}]}]}