{"stem":"too","instances":[{"docId":"1904-02-05","docUri":"1904-02-05.html","score":7,"contexts":[{"form":"too","weight":"1","pos":377,"context":" We don’t want to promise our honored readers <mark>too<\/mark> much. We want to make an effort to...","fid":"p__2"},{"form":"too","weight":"1","pos":1004,"context":"..., that someone who is a religious heretic is <mark>too<\/mark> nice to a job, an employment, too...","fid":"p__3"},{"form":"too","weight":"1","pos":1008,"context":"...too nice to a job, an employment, <mark>too<\/mark> nice to a business, a wife or simply...","fid":"p__3"},{"form":"too","weight":"1","pos":1013,"context":"...nice to a business, a wife or simply <mark>too<\/mark> nice to “society”, too nice to his children...","fid":"p__3"},{"form":"too","weight":"1","pos":1016,"context":"...a wife or simply too nice to “society”, <mark>too<\/mark> nice to his children - like he says -...","fid":"p__3"},{"form":"too","weight":"1","pos":2103,"context":".... Also pious, honest parents sometimes don’t care <mark>too<\/mark> much about educating their children Jewish so it would...","fid":"p__5"},{"form":"too","weight":"1","pos":2460,"context":"...until now. But sometimes, it is already <mark>too<\/mark> late. Or the daughter is “strong” enough,...","fid":"p__6"}]},{"docId":"1904-02-19","docUri":"1904-02-19.html","score":4,"contexts":[{"form":"too","weight":"1","pos":1803,"context":"...Triest and Dalmatia. Only if the demonstrations become <mark>too<\/mark> intense will the government intervene as they should not...","fid":"p__27"},{"form":"too","weight":"1","pos":2955,"context":"...Turkish tribe living in Macedonia) the reforms are <mark>too<\/mark> much. They claim that the Turkish government indulges...","fid":"p__10"},{"form":"too","weight":"1","pos":2967,"context":"...claim that the Turkish government indulges the revolutionaries way <mark>too<\/mark> much. And because they are aware that Turkey...","fid":"p__10"},{"form":"too","weight":"1","pos":3747,"context":"...been spoken already and filed and it is therefore <mark>too<\/mark> late to appeal. The lawyer then handed in...","fid":"p__8"}]},{"docId":"1904-03-04","docUri":"1904-03-04.html","score":4,"contexts":[{"form":"too","weight":"1","pos":949,"context":"...has not been a revolution, it is still <mark>too<\/mark> early for this because Russia is still too strong...","fid":"p__9"},{"form":"too","weight":"1","pos":956,"context":"...still too early for this because Russia is still <mark>too<\/mark> strong and could squash every revolution. However,...","fid":"p__9"},{"form":"too","weight":"1","pos":1418,"context":"...alone will not accomplish anything, because they are <mark>too<\/mark> weak and dispersed over various districts. They do...","fid":"p__13"},{"form":"too","weight":"1","pos":2944,"context":"...but cannot get them anywhere because they are all <mark>too<\/mark> slender. It will be a while until new...","fid":"p__17"}]},{"docId":"1904-02-26","docUri":"1904-02-26.html","score":2,"contexts":[{"form":"too","weight":"1","pos":275,"context":"...of blessed memories have said: “If you grasp <mark>too<\/mark> much, you will grasp nothing” and not to...","fid":"p__7"},{"form":"too","weight":"1","pos":283,"context":"..., you will grasp nothing” and not to put <mark>too<\/mark> much work on our backs. Therefore, we...","fid":"p__7"}]},{"docId":"1904-02-12","docUri":"1904-02-12.html","score":1,"contexts":[{"form":"too","weight":"1","pos":550,"context":"...remain quiet if someone complains that the teacher is <mark>too<\/mark> pious (usually a lawyer or a doctor or...","fid":"p__9"}]}]}