{"stem":"tsar","instances":[{"docId":"1904-02-12","docUri":"1904-02-12.html","score":3,"contexts":[{"form":"tsar","weight":"1","pos":2763,"context":"...- the Russian govenor in Asia - to the <mark>tsar<\/mark> [Nicholas II]: “I have to inform about..."},{"form":"tsar’s","weight":"1","pos":2926,"context":"...by the news of the first loss. The <mark>tsar’s<\/mark> ball has been cancelled because of it. The Russian...","fid":"p__7"},{"form":"tsar","weight":"1","pos":2971,"context":"...The govener Alekseyev sent the following telegram to the <mark>tsar<\/mark>: “On Monday, the Japanese troops, consiting...","fid":"p__12"}]}]}