{"stem":"undertak","instances":[{"docId":"1904-02-05","docUri":"1904-02-05.html","score":3,"contexts":[{"form":"undertaking","weight":"1","pos":667,"context":"...enemies, one will also deter from disturbing your <mark>undertaking<\/mark>, because the paper will not be a big...","fid":"p__4"},{"form":"undertaking","weight":"1","pos":702,"context":"...and you should also not be bothered in your <mark>undertaking<\/mark>, you have to work bravely and enthusiastically for...","fid":"p__4"},{"form":"undertaking","weight":"1","pos":729,"context":"...pact that this will also encourage you for your <mark>undertaking<\/mark> not to fear and to come to the conviction...","fid":"p__5"}]}]}