{"stem":"verdict","instances":[{"docId":"1904-02-19","docUri":"1904-02-19.html","score":4,"contexts":[{"form":"verdict","weight":"1","pos":3715,"context":"...but the court told him to wait until the <mark>verdict<\/mark> was sent to him. After some weeks the...","fid":"p__8"},{"form":"verdict","weight":"1","pos":3728,"context":"...some weeks the lawyer still has not received the <mark>verdict<\/mark> and turned to the court. The court told...","fid":"p__8"},{"form":"verdict","weight":"1","pos":3739,"context":"...the court. The court told him that the <mark>verdict<\/mark> has long been spoken already and filed and it...","fid":"p__8"},{"form":"verdict","weight":"1","pos":4279,"context":"...punish those who did not want to accept his <mark>verdict<\/mark>. ","fid":"p__3"}]}]}