{"place196.html":["place196"],"place221.html":["place221"],"place285.html":["place285"],"1904-03-01.html":["1904-03-01"],"pmb31261.html":["pmb31261"],"person206.html":["person206"],"place276.html":["place276"],"place290.html":["place290"],"place213.html":["place213"],"place134.html":["place134"],"place003.html":["place003"],"pmb36374.html":["pmb36374"],"place228.html":["place228"],"place242.html":["place242"],"place257.html":["place257"],"place312.html":["place312"],"person177.html":["person177"],"place009.html":["place009"],"place106.html":["place106"],"person022.html":["person022"],"place229.html":["place229"],"place315.html":["place315"],"person221.html":["person221"],"person197.html":["person197"],"place133.html":["place133"],"place016.html":["place016"],"place097.html":["place097"],"person198.html":["person198"],"place160.html":["place160"],"place260.html":["place260"],"place154.html":["place154"],"place193.html":["place193"],"place135.html":["place135"],"place082.html":["place082"],"place053.html":["place053"],"person064.html":["person064"],"person141.html":["person141"],"person126.html":["person126"],"place274.html":["place274"],"place088.html":["place088"],"place300.html":["place300"],"place209.html":["place209"],"place062.html":["place062"],"place215.html":["place215"],"person184.html":["person184"],"person140.html":["person140"],"place017.html":["place017"],"place108.html":["place108"],"person010.html":["person010"],"person163.html":["person163"],"place008.html":["place008"],"place046.html":["place046"],"place278.html":["place278"],"listbibl.html":["listbibl"],"person196.html":["person196"],"place264.html":["place264"],"place197.html":["place197"],"place297.html":["place297"],"person137.html":["person137"],"place304.html":["place304"],"place143.html":["place143"],"person116.html":["person116"],"ressources.html":["ressources"],"person149.html":["person149"],"person146.html":["person146"],"place091.html":["place091"],"place031.html":["place031"],"person166.html":["person166"],"place187.html":["place187"],"person145.html":["person145"],"place101.html":["place101"],"place244.html":["place244"],"place220.html":["place220"],"place096.html":["place096"],"place023.html":["place023"],"person111.html":["person111"],"person108.html":["person108"],"place237.html":["place237"],"pmb41244.html":["pmb41244"],"place301.html":["place301"],"person195.html":["person195"],"place223.html":["place223"],"place294.html":["place294"],"place207.html":["place207"],"place186.html":["place186"],"person207.html":["person207"],"place313.html":["place313"],"place202.html":["place202"],"place230.html":["place230"],"place258.html":["place258"],"person012.html":["person012"],"person062.html":["person062"],"person004.html":["person004"],"person118.html":["person118"],"place200.html":["place200"],"place034.html":["place034"],"place119.html":["place119"],"person223.html":["person223"],"person098.html":["person098"],"person121.html":["person121"],"person102.html":["person102"],"person179.html":["person179"],"place139.html":["place139"],"place138.html":["place138"],"place042.html":["place042"],"person128.html":["person128"],"place172.html":["place172"],"place173.html":["place173"],"person139.html":["person139"],"person106.html":["person106"],"person178.html":["person178"],"place210.html":["place210"],"place208.html":["place208"],"person210.html":["person210"],"place184.html":["place184"],"place112.html":["place112"],"place054.html":["place054"],"place030.html":["place030"],"person225.html":["person225"],"place311.html":["place311"],"place238.html":["place238"],"place117.html":["place117"],"place130.html":["place130"],"place296.html":["place296"],"person205.html":["person205"],"place083.html":["place083"],"person084.html":["person084"],"place040.html":["place040"],"place179.html":["place179"],"place155.html":["place155"],"place169.html":["place169"],"place036.html":["place036"],"place115.html":["place115"],"place224.html":["place224"],"place174.html":["place174"],"person053.html":["person053"],"place275.html":["place275"],"place166.html":["place166"],"place144.html":["place144"],"place279.html":["place279"],"person112.html":["person112"],"place317.html":["place317"],"place024.html":["place024"],"place020.html":["place020"],"place102.html":["place102"],"person122.html":["person122"],"place127.html":["place127"],"place064.html":["place064"],"place246.html":["place246"],"place026.html":["place026"],"person148.html":["person148"],"place015.html":["place015"],"person044.html":["person044"],"place217.html":["place217"],"person043.html":["person043"],"place098.html":["place098"],"person001.html":["person001"],"place171.html":["place171"],"person036.html":["person036"],"place049.html":["place049"],"place043.html":["place043"],"place051.html":["place051"],"place136.html":["place136"],"place156.html":["place156"],"person038.html":["person038"],"place092.html":["place092"],"place075.html":["place075"],"place022.html":["place022"],"place055.html":["place055"],"person066.html":["person066"],"person104.html":["person104"],"person073.html":["person073"],"person033.html":["person033"],"place029.html":["place029"],"place052.html":["place052"],"place243.html":["place243"],"place057.html":["place057"],"place240.html":["place240"],"place167.html":["place167"],"place141.html":["place141"],"place116.html":["place116"],"place033.html":["place033"],"place194.html":["place194"],"1904-02-05.html":["1904-02-05"],"place295.html":["place295"],"person202.html":["person202"],"place201.html":["place201"],"person176.html":["person176"],"person113.html":["person113"],"person015.html":["person015"],"person183.html":["person183"],"toc.html":["toc"],"person087.html":["person087"],"place056.html":["place056"],"person029.html":["person029"],"place227.html":["place227"],"place277.html":["place277"],"person085.html":["person085"],"place005.html":["place005"],"place109.html":["place109"],"person105.html":["person105"],"person186.html":["person186"],"person125.html":["person125"],"person151.html":["person151"],"place039.html":["place039"],"place254.html":["place254"],"place085.html":["place085"],"place104.html":["place104"],"place140.html":["place140"],"person181.html":["person181"],"place001.html":["place001"],"place068.html":["place068"],"place129.html":["place129"],"person204.html":["person204"],"person080.html":["person080"],"1904-03-08.html":["1904-03-08"],"person127.html":["person127"],"place149.html":["place149"],"place283.html":["place283"],"place177.html":["place177"],"place292.html":["place292"],"place122.html":["place122"],"listorg.html":["listorg"],"place233.html":["place233"],"person078.html":["person078"],"place118.html":["place118"],"person220.html":["person220"],"place303.html":["place303"],"place078.html":["place078"],"person201.html":["person201"],"place298.html":["place298"],"listplace.html":["listplace"],"person017.html":["person017"],"place103.html":["place103"],"place269.html":["place269"],"person219.html":["person219"],"person024.html":["person024"],"place014.html":["place014"],"place124.html":["place124"],"place121.html":["place121"],"person119.html":["person119"],"place178.html":["place178"],"place162.html":["place162"],"person162.html":["person162"],"place265.html":["place265"],"person152.html":["person152"],"person032.html":["person032"],"person075.html":["person075"],"place093.html":["place093"],"person209.html":["person209"],"1904-02-12.html":["1904-02-12"],"place305.html":["place305"],"pmb58510.html":["pmb58510"],"place204.html":["place204"],"person222.html":["person222"],"place291.html":["place291"],"place089.html":["place089"],"place145.html":["place145"],"person129.html":["person129"],"place105.html":["place105"],"place181.html":["place181"],"person042.html":["person042"],"person090.html":["person090"],"place273.html":["place273"],"place035.html":["place035"],"person194.html":["person194"],"place113.html":["place113"],"person100.html":["person100"],"person057.html":["person057"],"person045.html":["person045"],"place010.html":["place010"],"place170.html":["place170"],"place293.html":["place293"],"person190.html":["person190"],"person041.html":["person041"],"search.html":["search"],"imprint.html":["imprint"],"person133.html":["person133"],"place281.html":["place281"],"lk_fackel__95.html":["lk_fackel__95"],"place038.html":["place038"],"place176.html":["place176"],"place041.html":["place041"],"pmb62204.html":["pmb62204"],"place006.html":["place006"],"person192.html":["person192"],"place077.html":["place077"],"person136.html":["person136"],"place306.html":["place306"],"person110.html":["person110"],"place132.html":["place132"],"place114.html":["place114"],"place164.html":["place164"],"person155.html":["person155"],"place316.html":["place316"],"place198.html":["place198"],"place126.html":["place126"],"place060.html":["place060"],"place206.html":["place206"],"person007.html":["person007"],"person074.html":["person074"],"place050.html":["place050"],"person055.html":["person055"],"person014.html":["person014"],"place065.html":["place065"],"person147.html":["person147"],"place004.html":["place004"],"1904-03-15.html":["1904-03-15"],"place148.html":["place148"],"place107.html":["place107"],"person158.html":["person158"],"place021.html":["place021"],"place219.html":["place219"],"place146.html":["place146"],"place123.html":["place123"],"place302.html":["place302"],"place280.html":["place280"],"place152.html":["place152"],"place199.html":["place199"],"place161.html":["place161"],"place310.html":["place310"],"place019.html":["place019"],"place128.html":["place128"],"person030.html":["person030"],"place032.html":["place032"],"person049.html":["person049"],"person011.html":["person011"],"person088.html":["person088"],"person217.html":["person217"],"place270.html":["place270"],"person191.html":["person191"],"place191.html":["place191"],"listperson.html":["listperson"],"place076.html":["place076"],"person214.html":["person214"],"person056.html":["person056"],"person079.html":["person079"],"person188.html":["person188"],"person097.html":["person097"],"person164.html":["person164"],"place120.html":["place120"],"place063.html":["place063"],"place095.html":["place095"],"place189.html":["place189"],"person047.html":["person047"],"person175.html":["person175"],"place048.html":["place048"],"person172.html":["person172"],"person077.html":["person077"],"place073.html":["place073"],"place288.html":["place288"],"person093.html":["person093"],"place080.html":["place080"],"place157.html":["place157"],"pmb50491.html":["pmb50491"],"person094.html":["person094"],"person018.html":["person018"],"person040.html":["person040"],"place153.html":["place153"],"place226.html":["place226"],"person165.html":["person165"],"person138.html":["person138"],"place013.html":["place013"],"place163.html":["place163"],"place165.html":["place165"],"person193.html":["person193"],"place235.html":["place235"],"place002.html":["place002"],"person168.html":["person168"],"pmb62248.html":["pmb62248"],"person020.html":["person020"],"person174.html":["person174"],"person059.html":["person059"],"place252.html":["place252"],"place025.html":["place025"],"place255.html":["place255"],"index.html":["index"],"person046.html":["person046"],"person031.html":["person031"],"person072.html":["person072"],"person107.html":["person107"],"person215.html":["person215"],"person063.html":["person063"],"1904-03-29.html":["1904-03-29"],"person026.html":["person026"],"person180.html":["person180"],"place018.html":["place018"],"person211.html":["person211"],"place100.html":["place100"],"person067.html":["person067"],"place267.html":["place267"],"person048.html":["person048"],"place249.html":["place249"],"person008.html":["person008"],"person081.html":["person081"],"person052.html":["person052"],"place074.html":["place074"],"place007.html":["place007"],"place231.html":["place231"],"person054.html":["person054"],"person170.html":["person170"],"person123.html":["person123"],"place012.html":["place012"],"place185.html":["place185"],"place214.html":["place214"],"person060.html":["person060"],"place250.html":["place250"],"place253.html":["place253"],"person050.html":["person050"],"place299.html":["place299"],"place248.html":["place248"],"place188.html":["place188"],"person187.html":["person187"],"place203.html":["place203"],"person103.html":["person103"],"person199.html":["person199"],"place151.html":["place151"],"place125.html":["place125"],"person082.html":["person082"],"place314.html":["place314"],"person034.html":["person034"],"person131.html":["person131"],"place047.html":["place047"],"1904-02-19.html":["1904-02-19"],"place111.html":["place111"],"person006.html":["person006"],"1904-03-22.html":["1904-03-22"],"place259.html":["place259"],"place028.html":["place028"],"person035.html":["person035"],"person142.html":["person142"],"place286.html":["place286"],"person182.html":["person182"],"place061.html":["place061"],"person037.html":["person037"],"place234.html":["place234"],"place245.html":["place245"],"person115.html":["person115"],"person091.html":["person091"],"person021.html":["person021"],"place256.html":["place256"],"place069.html":["place069"],"place211.html":["place211"],"person092.html":["person092"],"person224.html":["person224"],"place086.html":["place086"],"place147.html":["place147"],"place150.html":["place150"],"place168.html":["place168"],"person218.html":["person218"],"place232.html":["place232"],"place308.html":["place308"],"place058.html":["place058"],"place059.html":["place059"],"person051.html":["person051"],"place268.html":["place268"],"person061.html":["person061"],"place205.html":["place205"],"place287.html":["place287"],"place225.html":["place225"],"person171.html":["person171"],"person086.html":["person086"],"person099.html":["person099"],"person083.html":["person083"],"place241.html":["place241"],"person101.html":["person101"],"person189.html":["person189"],"person132.html":["person132"],"place079.html":["place079"],"person130.html":["person130"],"place099.html":["place099"],"place158.html":["place158"],"place236.html":["place236"],"place037.html":["place037"],"person120.html":["person120"],"person114.html":["person114"],"person216.html":["person216"],"person159.html":["person159"],"person213.html":["person213"],"person208.html":["person208"],"1904-03-18.html":["1904-03-18"],"place070.html":["place070"],"place212.html":["place212"],"person124.html":["person124"],"person109.html":["person109"],"pmb29637.html":["pmb29637"],"place266.html":["place266"],"person069.html":["person069"],"place084.html":["place084"],"person025.html":["person025"],"person028.html":["person028"],"pmb42850.html":["pmb42850"],"place110.html":["place110"],"person002.html":["person002"],"about.html":["about"],"person009.html":["person009"],"person095.html":["person095"],"person070.html":["person070"],"person076.html":["person076"],"person096.html":["person096"],"1904-02-26.html":["1904-02-26"],"place251.html":["place251"],"place072.html":["place072"],"place142.html":["place142"],"person065.html":["person065"],"place262.html":["place262"],"person160.html":["person160"],"person227.html":["person227"],"place159.html":["place159"],"place182.html":["place182"],"person068.html":["person068"],"person144.html":["person144"],"place190.html":["place190"],"person153.html":["person153"],"place131.html":["place131"],"place261.html":["place261"],"place216.html":["place216"],"place195.html":["place195"],"person023.html":["person023"],"place309.html":["place309"],"person134.html":["person134"],"person058.html":["person058"],"person135.html":["person135"],"place284.html":["place284"],"place239.html":["place239"],"place067.html":["place067"],"place094.html":["place094"],"person200.html":["person200"],"place263.html":["place263"],"person156.html":["person156"],"place081.html":["place081"],"person027.html":["person027"],"person013.html":["person013"],"place222.html":["place222"],"person203.html":["person203"],"person154.html":["person154"],"place045.html":["place045"],"place027.html":["place027"],"place272.html":["place272"],"place180.html":["place180"],"pmb29823.html":["pmb29823"],"place289.html":["place289"],"place087.html":["place087"],"person150.html":["person150"],"person019.html":["person019"],"person016.html":["person016"],"person089.html":["person089"],"person117.html":["person117"],"place247.html":["place247"],"person039.html":["person039"],"person157.html":["person157"],"person167.html":["person167"],"1904-03-11.html":["1904-03-11"],"place090.html":["place090"],"place271.html":["place271"],"person161.html":["person161"],"1904-03-04.html":["1904-03-04"],"person173.html":["person173"],"1904-03-25.html":["1904-03-25"],"person071.html":["person071"],"place137.html":["place137"],"person212.html":["person212"],"place175.html":["place175"],"place183.html":["place183"],"person143.html":["person143"],"person226.html":["person226"],"place011.html":["place011"],"place307.html":["place307"],"place071.html":["place071"],"place192.html":["place192"],"lk_fackel__96.html":["lk_fackel__96"],"person003.html":["person003"],"person169.html":["person169"],"place218.html":["place218"],"person005.html":["person005"],"person185.html":["person185"]}